{"municipio": "penuelas", "sueldos": {"irregular": null, "else": [{"0": "Cat.", "1": "Desc.Categor\u00eda", "2": "Departamento", "3": "T\u00edtulo del Puesto", "4": "Cant.Empl.", "5": "Meses", "6": "SueldoMensual", "7": "SueldoAnual", "8": "7.65%", "9": "$ 150.00", "10": "Plan M\u00e9dico", "11": "Bono de Navidad", "12": "TOTAL"}, {"0": "C", "1": "Confianza", "2": "Legislatura Municipal", "3": "Secretaria Legislatura Municipal", "4": 1.0, "5": 12.0, "6": 2856.0, "7": 34272.0, "8": 2683.01, "9": "SI", "10": 1800.0, "11": 800.0, "12": 39555.01}, {"0": "C", "1": "Confianza", "2": "Oficina del Alcalde(sa)", "3": "Secretaria Alcalde", "4": 1.0, "5": 12.0, "6": 2803.0, "7": 33636.0, "8": 2634.35, "9": "SI", "10": 1800.0, "11": 800.0, "12": 38870.35}, {"0": "C", "1": "Confianza", "2": "Oficina del Alcalde(sa)", "3": "Ayudante Especial", "4": 1.0, "5": 12.0, "6": 2966.0, "7": 35592.0, "8": 2783.99, "9": "SI", "10": 1800.0, "11": 800.0, "12": 40975.99}, {"0": "C", "1": "Confianza", "2": "Oficina del Alcalde(sa)", "3": "Ayudante  Especial", "4": 1.0, "5": 12.0, "6": 2803.0, "7": 33636.0, "8": 2634.35, "9": "SI", "10": 1800.0, "11": 800.0, "12": 38870.35}, {"0": "R", "1": "Regular", "2": "Oficina del Alcalde(sa)", "3": "Auxiliar Administrativo I", "4": 1.0, "5": 12.0, "6": 1666.0, "7": 19992.0, "8": 1590.59, "9": "SI", "10": 1800.0, "11": 800.0, "12": 24182.59}, {"0": "C", "1": "Confianza", "2": "Oficina del Alcalde(sa)", "3": "Ayudante Especial", "4": 1.0, "5": 12.0, "6": 2110.0, "7": 25320.0, "8": 1998.18, "9": "SI", "10": 1800.0, "11": 800.0, "12": 29918.18}, {"0": "C", "1": "Confianza", "2": "Oficina del Alcalde(sa)", "3": "Ayudante  Especial", "4": 1.0, "5": 12.0, "6": 2803.0, "7": 33636.0, "8": 2634.35, "9": "SI", "10": 1800.0, "11": 800.0, "12": 38870.35}, {"0": "C", "1": "Confianza", "2": "Oficina del Alcalde(sa)", "3": "Conductor de Vehiculo Liviano", "4": 1.0, "5": 12.0, "6": 2110.0, "7": 25320.0, "8": 1998.18, "9": "SI", "10": 1800.0, "11": 800.0, "12": 29918.18}, {"0": "C", "1": "Confianza", "2": "Oficina del Alcalde(sa)", "3": "Ayudante  Especial", "4": 1.0, "5": 12.0, "6": 2110.0, "7": 25320.0, "8": 1998.18, "9": "SI", "10": 1800.0, "11": 800.0, "12": 29918.18}, {"0": "C", "1": "Confianza", "2": "Oficina del Alcalde(sa)", "3": "Alcalde", "4": 1.0, "5": 12.0, "6": 5000.0, "7": 60000.0, "8": 4590.0, "9": "SI", "10": 1800.0, "11": 0.0, "12": 66390.0}, {"0": "R", "1": "Regular", "2": "Oficina del Alcalde(sa)", "3": "Auxiliar Administrativo I", "4": 1.0, "5": 12.0, "6": 1409.0, "7": 16908.0, "8": 1354.66, "9": "SI", "10": 1800.0, "11": 800.0, "12": 20862.66}, {"0": "R", "1": "Regular", "2": "Oficina del Alcalde(sa)", "3": "Auxiliar Administrativo I", "4": 1.0, "5": 12.0, "6": 1409.0, "7": 16908.0, "8": 1354.66, "9": "SI", "10": 1800.0, "11": 800.0, "12": 20862.66}, {"0": "C", "1": "Confianza", "2": "Oficina del Alcalde(sa)", "3": "Chofer del Alcalde", "4": 1.0, "5": 12.0, "6": 2991.0, "7": 35892.0, "8": 2806.94, "9": "SI", "10": 1800.0, "11": 800.0, "12": 41298.94}, {"0": "R", "1": "Regular", "2": "Finanzas", "3": "Auxiliar Administrativo I", "4": 1.0, "5": 12.0, "6": 1409.0, "7": 16908.0, "8": 1354.66, "9": "SI", "10": 1800.0, "11": 800.0, "12": 20862.66}, {"0": "R", "1": "Regular", "2": "Finanzas", "3": "Oficial Pre-intervenciones", "4": 1.0, "5": 12.0, "6": 1713.0, "7": 20556.0, "8": 1633.73, "9": "SI", "10": 1800.0, "11": 800.0, "12": 24789.73}, {"0": "R", "1": "Regular", "2": "Finanzas", "3": "Contadora", "4": 1.0, "5": 12.0, "6": 1594.0, "7": 19128.0, "8": 1524.49, "9": "SI", "10": 1800.0, "11": 800.0, "12": 23252.49}, {"0": "R", "1": "Regular", "2": "Finanzas", "3": "Recaudador Oficial", "4": 1.0, "5": 12.0, "6": 1276.0, "7": 15312.0, "8": 1232.57, "9": "SI", "10": 1800.0, "11": 800.0, "12": 19144.57}, {"0": "R", "1": "Regular", "2": "Finanzas", "3": "Oficinista", "4": 1.0, "5": 12.0, "6": 1203.0, "7": 14436.0, "8": 1165.55, "9": "SI", "10": 1800.0, "11": 800.0, "12": 18201.55}, {"0": "R", "1": "Regular", "2": "Finanzas", "3": "Contadora", "4": 1.0, "5": 12.0, "6": 1594.0, "7": 19128.0, "8": 1524.49, "9": "SI", "10": 1800.0, "11": 800.0, "12": 23252.49}, {"0": "R", "1": "Regular", "2": "Finanzas", "3": "Pagador Oficial", "4": 1.0, "5": 12.0, "6": 1409.0, "7": 16908.0, "8": 1354.66, "9": "SI", "10": 1800.0, "11": 800.0, "12": 20862.66}, {"0": "R", "1": "Regular", "2": "Finanzas", "3": "Recaudador Auxiliar", "4": 1.0, "5": 12.0, "6": 1462.0, "7": 17544.0, "8": 1403.32, "9": "SI", "10": 1800.0, "11": 800.0, "12": 21547.32}, {"0": "R", "1": "Regular", "2": "Finanzas", "3": "Auxiliar Administrativo I", "4": 1.0, "5": 12.0, "6": 1520.0, "7": 18240.0, "8": 1456.56, "9": "SI", "10": 1800.0, "11": 800.0, "12": 22296.56}, {"0": "R", "1": "Regular", "2": "Finanzas", "3": "Auxiliar Administrativo I", "4": 1.0, "5": 12.0, "6": 1409.0, "7": 16908.0, "8": 1354.66, "9": "SI", "10": 1800.0, "11": 800.0, "12": 20862.66}, {"0": "C", "1": "Confianza", "2": "Finanzas", "3": "Directora de Finanzas", "4": 1.0, "5": 12.0, "6": 2976.0, "7": 35712.0, "8": 2793.17, "9": "SI", "10": 1800.0, "11": 800.0, "12": 41105.17}, {"0": "R", "1": "Regular", "2": "Finanzas", "3": "Auxiliar de Pre- Intervenciones", "4": 1.0, "5": 12.0, "6": 1323.0, "7": 15876.0, "8": 1275.71, "9": "SI", "10": 1800.0, "11": 800.0, "12": 19751.71}, {"0": "R", "1": "Regular", "2": "Obras P\u00fablicas", "3": "Trabajador", "4": 1.0, "5": 12.0, "6": 1247.0, "7": 14964.0, "8": 1205.95, "9": "SI", "10": 1800.0, "11": 800.0, "12": 18769.95}, {"0": "R", "1": "Regular", "2": "Obras P\u00fablicas", "3": "Conductor de Veh. Pesado", "4": 1.0, "5": 12.0, "6": 1410.0, "7": 16920.0, "8": 1355.58, "9": "SI", "10": 1800.0, "11": 800.0, "12": 20875.58}, {"0": "R", "1": "Regular", "2": "Obras P\u00fablicas", "3": "Trabajador", "4": 1.0, "5": 12.0, "6": 1179.0, "7": 14148.0, "8": 1143.52, "9": "SI", "10": 1800.0, "11": 800.0, "12": 17891.52}, {"0": "R", "1": "Regular", "2": "Obras P\u00fablicas", "3": "Trabajador", "4": 1.0, "5": 12.0, "6": 1179.0, "7": 14148.0, "8": 1143.52, "9": "SI", "10": 1800.0, "11": 800.0, "12": 17891.52}, {"0": "R", "1": "Regular", "2": "Obras P\u00fablicas", "3": "Conductor de Veh\u00edculo Pesado", "4": 1.0, "5": 12.0, "6": 1371.0, "7": 16452.0, "8": 1319.78, "9": "SI", "10": 1800.0, "11": 800.0, "12": 20371.78}, {"0": "R", "1": "Regular", "2": "Obras P\u00fablicas", "3": "Conductor de Veh\u00edculo Pesado", "4": 1.0, "5": 12.0, "6": 1371.0, "7": 16452.0, "8": 1319.78, "9": "SI", "10": 1800.0, "11": 800.0, "12": 20371.78}, {"0": "C", "1": "Confianza", "2": "Obras P\u00fablicas", "3": "Director de Obras P\u00fablicas", "4": 1.0, "5": 12.0, "6": 2810.0, "7": 33720.0, "8": 2640.78, "9": "SI", "10": 1800.0, "11": 800.0, "12": 38960.78}, {"0": "R", "1": "Regular", "2": "Obras P\u00fablicas", "3": "Supervisor de Transporte", "4": 1.0, "5": 12.0, "6": 1847.0, "7": 22164.0, "8": 1756.75, "9": "SI", "10": 1800.0, "11": 800.0, "12": 26520.75}, {"0": "R", "1": "Regular", "2": "Obras P\u00fablicas", "3": "Trabajador", "4": 1.0, "5": 12.0, "6": 1179.0, "7": 14148.0, "8": 1143.52, "9": "SI", "10": 1800.0, "11": 800.0, "12": 17891.52}, {"0": "R", "1": "Regular", "2": "Obras P\u00fablicas", "3": "Trabajador", "4": 1.0, "5": 12.0, "6": 1247.0, "7": 14964.0, "8": 1205.95, "9": "SI", "10": 1800.0, "11": 800.0, "12": 18769.95}, {"0": "R", "1": "Regular", "2": "Obras P\u00fablicas", "3": "Conserje", "4": 1.0, "5": 12.0, "6": 1394.0, "7": 16728.0, "8": 1340.89, "9": "SI", "10": 1800.0, "11": 800.0, "12": 20668.89}, {"0": "R", "1": "Regular", "2": "Obras P\u00fablicas", "3": "Supervidor de Limpieza P\u00fablica", "4": 1.0, "5": 12.0, "6": 1437.0, "7": 17244.0, "8": 1380.37, "9": "SI", "10": 1800.0, "11": 800.0, "12": 21224.37}, {"0": "R", "1": "Regular", "2": "Obras P\u00fablicas", "3": "Conserje", "4": 1.0, "5": 12.0, "6": 1394.0, "7": 16728.0, "8": 1340.89, "9": "SI", "10": 1800.0, "11": 800.0, "12": 20668.89}, {"0": "R", "1": "Regular", "2": "Obras P\u00fablicas", "3": "Encargado de Brigada", "4": 1.0, "5": 12.0, "6": 1227.0, "7": 14724.0, "8": 1187.59, "9": "SI", "10": 1800.0, "11": 800.0, "12": 18511.59}, {"0": "C", "1": "Confianza", "2": "Obras P\u00fablicas", "3": "Coord. de Planificaci\u00f3n y Des.", "4": 1.0, "5": 12.0, "6": 2899.0, "7": 34788.0, "8": 2722.48, "9": "SI", "10": 1800.0, "11": 800.0, "12": 40110.48}, {"0": "R", "1": "Regular", "2": "Obras P\u00fablicas", "3": "Trabajador", "4": 1.0, "5": 12.0, "6": 1394.0, "7": 16728.0, "8": 1340.89, "9": "SI", "10": 1800.0, "11": 800.0, "12": 20668.89}, {"0": "R", "1": "Regular", "2": "Obras P\u00fablicas", "3": "Encargado del Cementerio", "4": 1.0, "5": 12.0, "6": 1334.0, "7": 16008.0, "8": 1285.81, "9": "SI", "10": 1800.0, "11": 800.0, "12": 19893.81}, {"0": "R", "1": "Regular", "2": "Obras P\u00fablicas", "3": "Trabajador", "4": 1.0, "5": 12.0, "6": 1247.0, "7": 14964.0, "8": 1205.95, "9": "SI", "10": 1800.0, "11": 800.0, "12": 18769.95}, {"0": "R", "1": "Regular", "2": "Obras P\u00fablicas", "3": "Trabajador", "4": 1.0, "5": 12.0, "6": 1179.0, "7": 14148.0, "8": 1143.52, "9": "SI", "10": 1800.0, "11": 800.0, "12": 17891.52}, {"0": "R", "1": "Regular", "2": "Obras P\u00fablicas", "3": "Conductor de Veh\u00edculo Pesado", "4": 1.0, "5": 12.0, "6": 1410.0, "7": 16920.0, "8": 1355.58, "9": "SI", "10": 1800.0, "11": 800.0, "12": 20875.58}, {"0": "R", "1": "Regular", "2": "Obras P\u00fablicas", "3": "Conductor de Vehiculo Liviano", "4": 1.0, "5": 12.0, "6": 1422.0, "7": 17064.0, "8": 1366.6, "9": "SI", "10": 1800.0, "11": 800.0, "12": 21030.6}, {"0": "R", "1": "Regular", "2": "Obras P\u00fablicas", "3": "Conductor de Vehiculo Liviano", "4": 1.0, "5": 12.0, "6": 1634.0, "7": 19608.0, "8": 1561.21, "9": "SI", "10": 1800.0, "11": 800.0, "12": 23769.21}, {"0": "R", "1": "Regular", "2": "Obras P\u00fablicas", "3": "Trabajador", "4": 1.0, "5": 12.0, "6": 1179.0, "7": 14148.0, "8": 1143.52, "9": "SI", "10": 1800.0, "11": 800.0, "12": 17891.52}, {"0": "R", "1": "Regular", "2": "Obras P\u00fablicas", "3": "Conductor de Veh\u00edculo Pesado", "4": 1.0, "5": 12.0, "6": 1491.0, "7": 17892.0, "8": 1429.94, "9": "SI", "10": 1800.0, "11": 800.0, "12": 21921.94}, {"0": "R", "1": "Regular", "2": "Obras P\u00fablicas", "3": "Trabajador", "4": 1.0, "5": 12.0, "6": 1394.0, "7": 16728.0, "8": 1340.89, "9": "SI", "10": 1800.0, "11": 800.0, "12": 20668.89}, {"0": "R", "1": "Regular", "2": "Obras P\u00fablicas", "3": "Conductor de Vehiculo Pesado", "4": 1.0, "5": 12.0, "6": 1227.0, "7": 14724.0, "8": 1187.59, "9": "SI", "10": 1800.0, "11": 800.0, "12": 18511.59}, {"0": "R", "1": "Regular", "2": "Obras P\u00fablicas", "3": "Trabajador", "4": 1.0, "5": 12.0, "6": 1179.0, "7": 14148.0, "8": 1143.52, "9": "SI", "10": 1800.0, "11": 800.0, "12": 17891.52}, {"0": "R", "1": "Regular", "2": "Obras P\u00fablicas", "3": "Trabajador", "4": 1.0, "5": 12.0, "6": 1179.0, "7": 14148.0, "8": 1143.52, "9": "SI", "10": 1800.0, "11": 800.0, "12": 17891.52}, {"0": "R", "1": "Regular", "2": "Obras P\u00fablicas", "3": "Supervisor Limpieza P\u00fablica", "4": 1.0, "5": 12.0, "6": 1699.0, "7": 20388.0, "8": 1620.88, "9": "SI", "10": 1800.0, "11": 800.0, "12": 24608.88}, {"0": "R", "1": "Regular", "2": "Obras P\u00fablicas", "3": "Oficinista", "4": 1.0, "5": 12.0, "6": 1272.0, "7": 15264.0, "8": 1228.9, "9": "SI", "10": 1800.0, "11": 800.0, "12": 19092.9}, {"0": "R", "1": "Regular", "2": "Obras P\u00fablicas", "3": "Conductor de Veh\u00edculo Pesado", "4": 1.0, "5": 12.0, "6": 1450.0, "7": 17400.0, "8": 1392.3, "9": "SI", "10": 1800.0, "11": 800.0, "12": 21392.3}, {"0": "R", "1": "Regular", "2": "Obras P\u00fablicas", "3": "Trabajador", "4": 1.0, "5": 12.0, "6": 1179.0, "7": 14148.0, "8": 1143.52, "9": "SI", "10": 1800.0, "11": 800.0, "12": 17891.52}, {"0": "R", "1": "Regular", "2": "Obras P\u00fablicas", "3": "Trabajador", "4": 1.0, "5": 12.0, "6": 1179.0, "7": 14148.0, "8": 1143.52, "9": "SI", "10": 1800.0, "11": 800.0, "12": 17891.52}, {"0": "R", "1": "Regular", "2": "Obras P\u00fablicas", "3": "Trabajador", "4": 1.0, "5": 12.0, "6": 1394.0, "7": 16728.0, "8": 1340.89, "9": "SI", "10": 1800.0, "11": 800.0, "12": 20668.89}, {"0": "R", "1": "Regular", "2": "Obras P\u00fablicas", "3": "Trabajador", "4": 1.0, "5": 12.0, "6": 1394.0, "7": 16728.0, "8": 1340.89, "9": "SI", "10": 1800.0, "11": 800.0, "12": 20668.89}, {"0": "R", "1": "Regular", "2": "Obras P\u00fablicas", "3": "Trabajador", "4": 1.0, "5": 12.0, "6": 1179.0, "7": 14148.0, "8": 1143.52, "9": "SI", "10": 1800.0, "11": 800.0, "12": 17891.52}, {"0": "C", "1": "Confianza", "2": "Obras P\u00fablicas", "3": "Ayudante Especial", "4": 1.0, "5": 12.0, "6": 1055.0, "7": 12660.0, "8": 1029.69, "9": "SI", "10": 1800.0, "11": 800.0, "12": 16289.69}, {"0": "R", "1": "Regular", "2": "Obras P\u00fablicas", "3": "Trabajador", "4": 1.0, "5": 12.0, "6": 1179.0, "7": 14148.0, "8": 1143.52, "9": "SI", "10": 1800.0, "11": 800.0, "12": 17891.52}, {"0": "R", "1": "Regular", "2": "Oficina Municipal Manejo de", "3": "Conductor de Veh\u00edculo Pesado", "4": 1.0, "5": 12.0, "6": 1450.0, "7": 17400.0, "8": 1392.3, "9": "SI", "10": 1800.0, "11": 800.0, "12": 21392.3}, {"0": "R", "1": "Regular", "2": "Oficina Municipal Manejo de", "3": "Conductor de Vehiculo Pesado", "4": 1.0, "5": 12.0, "6": 1450.0, "7": 17400.0, "8": 1392.3, "9": "SI", "10": 1800.0, "11": 800.0, "12": 21392.3}, {"0": "R", "1": "Regular", "2": "Oficina Municipal Manejo de", "3": "Ayudante de Electricista", "4": 1.0, "5": 12.0, "6": 1203.0, "7": 14436.0, "8": 1165.55, "9": "SI", "10": 1800.0, "11": 800.0, "12": 18201.55}, {"0": "R", "1": "Regular", "2": "Oficina Municipal Manejo de", "3": "Trabajador", "4": 1.0, "5": 12.0, "6": 1179.0, "7": 14148.0, "8": 1143.52, "9": "SI", "10": 1800.0, "11": 800.0, "12": 17891.52}, {"0": "R", "1": "Regular", "2": "Oficina Municipal Manejo de", "3": "Conserje", "4": 1.0, "5": 12.0, "6": 1247.0, "7": 14964.0, "8": 1205.95, "9": "SI", "10": 1800.0, "11": 800.0, "12": 18769.95}, {"0": "R", "1": "Regular", "2": "Oficina Municipal Manejo de", "3": "Ayudante de Electricista", "4": 1.0, "5": 12.0, "6": 1203.0, "7": 14436.0, "8": 1165.55, "9": "SI", "10": 1800.0, "11": 800.0, "12": 18201.55}, {"0": "R", "1": "Regular", "2": "Oficina Municipal Manejo de", "3": "Conductor de Veh\u00edculo Pesado", "4": 1.0, "5": 12.0, "6": 1227.0, "7": 14724.0, "8": 1187.59, "9": "SI", "10": 1800.0, "11": 800.0, "12": 18511.59}, {"0": "R", "1": "Regular", "2": "Oficina Municipal Manejo de", "3": "Conductor de Vehiculo Liviano", "4": 1.0, "5": 12.0, "6": 1433.0, "7": 17196.0, "8": 1376.69, "9": "SI", "10": 1800.0, "11": 800.0, "12": 21172.69}, {"0": "R", "1": "Regular", "2": "Oficina Municipal Manejo de", "3": "Oficinista", "4": 1.0, "5": 12.0, "6": 1203.0, "7": 14436.0, "8": 1165.55, "9": "SI", "10": 1800.0, "11": 800.0, "12": 18201.55}, {"0": "R", "1": "Regular", "2": "Oficina Municipal Manejo de", "3": "Trabajador", "4": 1.0, "5": 12.0, "6": 628.76, "7": 7545.12, "8": 638.4, "9": "SI", "10": 1800.0, "11": 800.0, "12": 10783.52}, {"0": "R", "1": "Regular", "2": "Oficina Municipal Manejo de", "3": "Sub-director de Manejo de", "4": 1.0, "5": 12.0, "6": 1466.0, "7": 17592.0, "8": 1406.99, "9": "SI", "10": 1800.0, "11": 800.0, "12": 21598.99}, {"0": "R", "1": "Regular", "2": "Oficina Municipal Manejo de", "3": "Conductor de Vehiculo Liviano", "4": 1.0, "5": 12.0, "6": 1422.0, "7": 17064.0, "8": 1366.6, "9": "SI", "10": 1800.0, "11": 800.0, "12": 21030.6}, {"0": "R", "1": "Regular", "2": "Oficina Municipal Manejo de", "3": "Coordinador de Busqueda y Rescate", "4": 1.0, "5": 12.0, "6": 1276.0, "7": 15312.0, "8": 1232.57, "9": "SI", "10": 1800.0, "11": 800.0, "12": 19144.57}, {"0": "R", "1": "Regular", "2": "Oficina Municipal Manejo de", "3": "Encargado de Brigada", "4": 1.0, "5": 12.0, "6": 1491.0, "7": 17892.0, "8": 1429.94, "9": "SI", "10": 1800.0, "11": 800.0, "12": 21921.94}, {"0": "R", "1": "Regular", "2": "Oficina Municipal Manejo de", "3": "Auxiliar Administrativo I (32.5hr)", "4": 1.0, "5": 12.0, "6": 1221.13, "7": 14653.56, "8": 1182.2, "9": "SI", "10": 1800.0, "11": 800.0, "12": 18435.76}, {"0": "R", "1": "Regular", "2": "Oficina Municipal Manejo de", "3": "Trabajador", "4": 1.0, "5": 12.0, "6": 1179.0, "7": 14148.0, "8": 1143.52, "9": "SI", "10": 1800.0, "11": 800.0, "12": 17891.52}, {"0": "R", "1": "Regular", "2": "Guardia Municipal", "3": "Polic\u00eda Municipal", "4": 1.0, "5": 12.0, "6": 1667.0, "7": 20004.0, "8": 1591.51, "9": "SI", "10": 1800.0, "11": 800.0, "12": 24195.51}, {"0": "R", "1": "Regular", "2": "Guardia Municipal", "3": "Polic\u00eda Municipal", "4": 1.0, "5": 12.0, "6": 1667.0, "7": 20004.0, "8": 1591.51, "9": "SI", "10": 1800.0, "11": 800.0, "12": 24195.51}, {"0": "R", "1": "Regular", "2": "Guardia Municipal", "3": "Sargento", "4": 1.0, "5": 12.0, "6": 1922.0, "7": 23064.0, "8": 1825.6, "9": "SI", "10": 1800.0, "11": 800.0, "12": 27489.6}, {"0": "C", "1": "Confianza", "2": "Guardia Municipal", "3": "Comisionado de la Policia", "4": 1.0, "5": 12.0, "6": 2310.0, "7": 27720.0, "8": 2181.78, "9": "SI", "10": 1800.0, "11": 800.0, "12": 32501.78}, {"0": "R", "1": "Regular", "2": "Guardia Municipal", "3": "Polic\u00eda Municipal", "4": 1.0, "5": 12.0, "6": 1667.0, "7": 20004.0, "8": 1591.51, "9": "SI", "10": 1800.0, "11": 800.0, "12": 24195.51}, {"0": "R", "1": "Regular", "2": "Guardia Municipal", "3": "Trabajador (20 hrs.)", "4": 1.0, "5": 12.0, "6": 743.42, "7": 8921.04, "8": 743.66, "9": "SI", "10": 1800.0, "11": 800.0, "12": 12264.7}, {"0": "R", "1": "Regular", "2": "Guardia Municipal", "3": "Auxiliar Administrativo I", "4": 1.0, "5": 12.0, "6": 1409.0, "7": 16908.0, "8": 1354.66, "9": "SI", "10": 1800.0, "11": 800.0, "12": 20862.66}, {"0": "R", "1": "Regular", "2": "Guardia Municipal", "3": "Polic\u00eda Municipal", "4": 1.0, "5": 12.0, "6": 1667.0, "7": 20004.0, "8": 1591.51, "9": "SI", "10": 1800.0, "11": 800.0, "12": 24195.51}, {"0": "R", "1": "Regular", "2": "Guardia Municipal", "3": "Sargento", "4": 1.0, "5": 12.0, "6": 1922.0, "7": 23064.0, "8": 1825.6, "9": "SI", "10": 1800.0, "11": 800.0, "12": 27489.6}, {"0": "R", "1": "Regular", "2": "Guardia Municipal", "3": "Polic\u00eda Municipal", "4": 1.0, "5": 12.0, "6": 1667.0, "7": 20004.0, "8": 1591.51, "9": "SI", "10": 1800.0, "11": 800.0, "12": 24195.51}, {"0": "R", "1": "Regular", "2": "Guardia Municipal", "3": "Polic\u00eda Municipal", "4": 1.0, "5": 12.0, "6": 1667.0, "7": 20004.0, "8": 1591.51, "9": "SI", "10": 1800.0, "11": 800.0, "12": 24195.51}, {"0": "C", "1": "Confianza", "2": "Recursos Humanos", "3": "Director de Recursos Humanos", "4": 1.0, "5": 12.0, "6": 2858.0, "7": 34296.0, "8": 2684.84, "9": "SI", "10": 1800.0, "11": 800.0, "12": 39580.84}, {"0": "R", "1": "Regular", "2": "Recursos Humanos", "3": "Oficinista", "4": 1.0, "5": 12.0, "6": 1345.0, "7": 16140.0, "8": 1295.91, "9": "SI", "10": 1800.0, "11": 800.0, "12": 20035.91}, {"0": "R", "1": "Regular", "2": "Recursos Humanos", "3": "Oficinista", "4": 1.0, "5": 12.0, "6": 1203.0, "7": 14436.0, "8": 1165.55, "9": "SI", "10": 1800.0, "11": 800.0, "12": 18201.55}, {"0": "R", "1": "Regular", "2": "Recursos Humanos", "3": "Oficial de N\u00f3minas", "4": 1.0, "5": 12.0, "6": 1409.0, "7": 16908.0, "8": 1354.66, "9": "SI", "10": 1800.0, "11": 800.0, "12": 20862.66}, {"0": "R", "1": "Regular", "2": "Recursos Humanos", "3": "Oficinista", "4": 1.0, "5": 12.0, "6": 1308.0, "7": 15696.0, "8": 1261.94, "9": "SI", "10": 1800.0, "11": 800.0, "12": 19557.94}, {"0": "R", "1": "Regular", "2": "Recursos Humanos", "3": "Oficinista", "4": 1.0, "5": 12.0, "6": 1203.0, "7": 14436.0, "8": 1165.55, "9": "SI", "10": 1800.0, "11": 800.0, "12": 18201.55}, {"0": "R", "1": "Regular", "2": "Recursos Humanos", "3": "Oficinista", "4": 1.0, "5": 12.0, "6": 1272.0, "7": 15264.0, "8": 1228.9, "9": "SI", "10": 1800.0, "11": 800.0, "12": 19092.9}, {"0": "R", "1": "Regular", "2": "Recursos Humanos", "3": "Auxiliar Administativo II", "4": 1.0, "5": 12.0, "6": 1520.0, "7": 18240.0, "8": 1456.56, "9": "SI", "10": 1800.0, "11": 800.0, "12": 22296.56}, {"0": "R", "1": "Regular", "2": "Recursos Humanos", "3": "Oficinista", "4": 1.0, "5": 12.0, "6": 1422.0, "7": 17064.0, "8": 1366.6, "9": "SI", "10": 1800.0, "11": 800.0, "12": 21030.6}, {"0": "R", "1": "Regular", "2": "Recursos Humanos", "3": "Oficinista", "4": 1.0, "5": 12.0, "6": 1203.0, "7": 14436.0, "8": 1165.55, "9": "SI", "10": 1800.0, "11": 800.0, "12": 18201.55}, {"0": "R", "1": "Regular", "2": "Recursos Humanos", "3": "Conserje", "4": 1.0, "5": 12.0, "6": 1247.0, "7": 14964.0, "8": 1205.95, "9": "SI", "10": 1800.0, "11": 800.0, "12": 18769.95}, {"0": "R", "1": "Regular", "2": "Recreaci\u00f3n y Deportes", "3": "Trabajador", "4": 1.0, "5": 12.0, "6": 1179.0, "7": 14148.0, "8": 1143.52, "9": "SI", "10": 1800.0, "11": 800.0, "12": 17891.52}, {"0": "R", "1": "Regular", "2": "Recreaci\u00f3n y Deportes", "3": "Trabajador", "4": 1.0, "5": 12.0, "6": 1394.0, "7": 16728.0, "8": 1340.89, "9": "SI", "10": 1800.0, "11": 800.0, "12": 20668.89}, {"0": "R", "1": "Regular", "2": "Recreaci\u00f3n y Deportes", "3": "Oficinista", "4": 1.0, "5": 12.0, "6": 1203.0, "7": 14436.0, "8": 1165.55, "9": "SI", "10": 1800.0, "11": 800.0, "12": 18201.55}, {"0": "R", "1": "Regular", "2": "Recreaci\u00f3n y Deportes", "3": "Trabajador", "4": 1.0, "5": 12.0, "6": 1394.0, "7": 16728.0, "8": 1340.89, "9": "SI", "10": 1800.0, "11": 800.0, "12": 20668.89}, {"0": "R", "1": "Regular", "2": "Recreaci\u00f3n y Deportes", "3": "L\u00edder Recreativo", "4": 1.0, "5": 12.0, "6": 1297.0, "7": 15564.0, "8": 1251.85, "9": "SI", "10": 1800.0, "11": 800.0, "12": 19415.85}, {"0": "C", "1": "Confianza", "2": "Recreaci\u00f3n y Deportes", "3": "Director de Recreaci\u00f3n y Deportes", "4": 1.0, "5": 12.0, "6": 2310.0, "7": 27720.0, "8": 2181.78, "9": "SI", "10": 1800.0, "11": 800.0, "12": 32501.78}, {"0": "R", "1": "Regular", "2": "Recreaci\u00f3n y Deportes", "3": "Secretaria II", "4": 1.0, "5": 12.0, "6": 1467.0, "7": 17604.0, "8": 1407.91, "9": "SI", "10": 1800.0, "11": 800.0, "12": 21611.91}, {"0": "R", "1": "Regular", "2": "Recreaci\u00f3n y Deportes", "3": "Trabajador", "4": 1.0, "5": 12.0, "6": 1179.0, "7": 14148.0, "8": 1143.52, "9": "SI", "10": 1800.0, "11": 800.0, "12": 17891.52}, {"0": "R", "1": "Regular", "2": "Recreaci\u00f3n y Deportes", "3": "Trabajador", "4": 1.0, "5": 12.0, "6": 1179.0, "7": 14148.0, "8": 1143.52, "9": "SI", "10": 1800.0, "11": 800.0, "12": 17891.52}, {"0": "R", "1": "Regular", "2": "Recreaci\u00f3n y Deportes", "3": "Trabajador", "4": 1.0, "5": 12.0, "6": 1179.0, "7": 14148.0, "8": 1143.52, "9": "SI", "10": 1800.0, "11": 800.0, "12": 17891.52}, {"0": "R", "1": "Regular", "2": "Recreaci\u00f3n y Deportes", "3": "Lider Recreativo", "4": 1.0, "5": 12.0, "6": 1227.0, "7": 14724.0, "8": 1187.59, "9": "SI", "10": 1800.0, "11": 800.0, "12": 18511.59}, {"0": "R", "1": "Regular", "2": "Recreaci\u00f3n y Deportes", "3": "Encargado de Brigada", "4": 1.0, "5": 12.0, "6": 1450.0, "7": 17400.0, "8": 1392.3, "9": "SI", "10": 1800.0, "11": 800.0, "12": 21392.3}, {"0": "R", "1": "Regular", "2": "Recreaci\u00f3n y Deportes", "3": "Guardian de Seguridad", "4": 1.0, "5": 12.0, "6": 1247.0, "7": 14964.0, "8": 1205.95, "9": "SI", "10": 1800.0, "11": 800.0, "12": 18769.95}, {"0": "R", "1": "Regular", "2": "Recreaci\u00f3n y Deportes", "3": "Guardia de Seguridad", "4": 1.0, "5": 12.0, "6": 1318.0, "7": 15816.0, "8": 1271.12, "9": "SI", "10": 1800.0, "11": 800.0, "12": 19687.12}, {"0": "R", "1": "Regular", "2": "Recreaci\u00f3n y Deportes", "3": "Guardia de Seguridad", "4": 1.0, "5": 12.0, "6": 1547.0, "7": 18564.0, "8": 1481.35, "9": "SI", "10": 1800.0, "11": 800.0, "12": 22645.35}, {"0": "R", "1": "Regular", "2": "Recreaci\u00f3n y Deportes", "3": "Trabajador", "4": 1.0, "5": 12.0, "6": 1297.0, "7": 15564.0, "8": 1251.85, "9": "SI", "10": 1800.0, "11": 800.0, "12": 19415.85}, {"0": "R", "1": "Regular", "2": "Centro de Envejecientes", "3": "Encargada de Cocina", "4": 1.0, "5": 12.0, "6": 1410.0, "7": 16920.0, "8": 1355.58, "9": "SI", "10": 1800.0, "11": 800.0, "12": 20875.58}, {"0": "R", "1": "Regular", "2": "Centro de Envejecientes", "3": "Conserje", "4": 1.0, "5": 12.0, "6": 1179.0, "7": 14148.0, "8": 1143.52, "9": "SI", "10": 1800.0, "11": 800.0, "12": 17891.52}, {"0": "R", "1": "Regular", "2": "Centro de Envejecientes", "3": "Oficinista", "4": 1.0, "5": 12.0, "6": 1203.0, "7": 14436.0, "8": 1165.55, "9": "SI", "10": 1800.0, "11": 800.0, "12": 18201.55}, {"0": "R", "1": "Regular", "2": "Centro de Envejecientes", "3": "Conductor de Guagua", "4": 1.0, "5": 12.0, "6": 1227.0, "7": 14724.0, "8": 1187.59, "9": "SI", "10": 1800.0, "11": 800.0, "12": 18511.59}, {"0": "C", "1": "Confianza", "2": "Centro de Envejecientes", "3": "Directora Centro de Envejecientes", "4": 1.0, "5": 12.0, "6": 2739.0, "7": 32868.0, "8": 2575.6, "9": "SI", "10": 1800.0, "11": 800.0, "12": 38043.6}, {"0": "R", "1": "Regular", "2": "Centro de Envejecientes", "3": "Trabajador", "4": 1.0, "5": 12.0, "6": 1179.0, "7": 14148.0, "8": 1143.52, "9": "SI", "10": 1800.0, "11": 800.0, "12": 17891.52}, {"0": "R", "1": "Regular", "2": "Centro de Envejecientes", "3": "Oficinista", "4": 1.0, "5": 12.0, "6": 1345.0, "7": 16140.0, "8": 1295.91, "9": "SI", "10": 1800.0, "11": 800.0, "12": 20035.91}, {"0": "R", "1": "Regular", "2": "Centro de Envejecientes", "3": "Cocinero", "4": 1.0, "5": 12.0, "6": 1247.0, "7": 14964.0, "8": 1205.95, "9": "SI", "10": 1800.0, "11": 800.0, "12": 18769.95}, {"0": "R", "1": "Regular", "2": "Aportaciones Federales", "3": "Oficinista", "4": 1.0, "5": 12.0, "6": 1203.0, "7": 14436.0, "8": 1165.55, "9": "SI", "10": 1800.0, "11": 800.0, "12": 18201.55}, {"0": "R", "1": "Regular", "2": "Aportaciones Federales", "3": "Secretaria I", "4": 1.0, "5": 12.0, "6": 1438.0, "7": 17256.0, "8": 1381.28, "9": "SI", "10": 1800.0, "11": 800.0, "12": 21237.28}, {"0": "R", "1": "Regular", "2": "Aportaciones Federales", "3": "Trabajador", "4": 1.0, "5": 12.0, "6": 1179.0, "7": 14148.0, "8": 1143.52, "9": "SI", "10": 1800.0, "11": 800.0, "12": 17891.52}, {"0": "R", "1": "Regular", "2": "Aportaciones Federales", "3": "Encargado de Brigada", "4": 1.0, "5": 12.0, "6": 1261.0, "7": 15132.0, "8": 1218.8, "9": "SI", "10": 1800.0, "11": 800.0, "12": 18950.8}, {"0": "C", "1": "Confianza", "2": "Aportaciones Federales", "3": "Directora Programas Federales", "4": 1.0, "5": 12.0, "6": 2739.0, "7": 32868.0, "8": 2575.6, "9": "SI", "10": 1800.0, "11": 800.0, "12": 38043.6}, {"0": "R", "1": "Regular", "2": "Aportaciones Federales", "3": "Trabajador", "4": 1.0, "5": 12.0, "6": 1394.0, "7": 16728.0, "8": 1340.89, "9": "SI", "10": 1800.0, "11": 800.0, "12": 20668.89}, {"0": "R", "1": "Regular", "2": "Aportaciones Federales", "3": "Auxiliar Administrativo I", "4": 1.0, "5": 12.0, "6": 1449.0, "7": 17388.0, "8": 1391.38, "9": "SI", "10": 1800.0, "11": 800.0, "12": 21379.38}, {"0": "R", "1": "Regular", "2": "Aportaciones Federales", "3": "Trabajador", "4": 1.0, "5": 12.0, "6": 1212.0, "7": 14544.0, "8": 1173.82, "9": "SI", "10": 1800.0, "11": 800.0, "12": 18317.82}, {"0": "R", "1": "Regular", "2": "Aportaciones Federales", "3": "Trabajador", "4": 1.0, "5": 12.0, "6": 1179.0, "7": 14148.0, "8": 1143.52, "9": "SI", "10": 1800.0, "11": 800.0, "12": 17891.52}, {"0": "C", "1": "Confianza", "2": "Aportaciones Federales", "3": "Coordinadora  Prog. Federales", "4": 1.0, "5": 12.0, "6": 3107.0, "7": 37284.0, "8": 2913.43, "9": "SI", "10": 1800.0, "11": 800.0, "12": 42797.43}, {"0": "R", "1": "Regular", "2": "Aportaciones Federales", "3": "Trabajador", "4": 1.0, "5": 12.0, "6": 1179.0, "7": 14148.0, "8": 1143.52, "9": "SI", "10": 1800.0, "11": 800.0, "12": 17891.52}, {"0": "R", "1": "Regular", "2": "Aportaciones Federales", "3": "Trabajador", "4": 1.0, "5": 12.0, "6": 1422.0, "7": 17064.0, "8": 1366.6, "9": "SI", "10": 1800.0, "11": 800.0, "12": 21030.6}, {"0": "R", "1": "Regular", "2": "Cultura y Turismo", "3": "Trabajador", "4": 1.0, "5": 12.0, "6": 1179.0, "7": 14148.0, "8": 1143.52, "9": "SI", "10": 1800.0, "11": 800.0, "12": 17891.52}, {"0": "C", "1": "Confianza", "2": "Cultura y Turismo", "3": "Directora de Arte y Cultura", "4": 1.0, "5": 12.0, "6": 2588.0, "7": 31056.0, "8": 2436.98, "9": "SI", "10": 1800.0, "11": 800.0, "12": 36092.98}, {"0": "R", "1": "Regular", "2": "Cultura y Turismo", "3": "Guardi\u00e1n de Seguridad", "4": 1.0, "5": 12.0, "6": 1318.0, "7": 15816.0, "8": 1271.12, "9": "SI", "10": 1800.0, "11": 800.0, "12": 19687.12}, {"0": "R", "1": "Regular", "2": "Cultura y Turismo", "3": "Trabajador", "4": 1.0, "5": 12.0, "6": 1179.0, "7": 14148.0, "8": 1143.52, "9": "SI", "10": 1800.0, "11": 800.0, "12": 17891.52}, {"0": "R", "1": "Regular", "2": "Asuntos del Ciudadano", "3": "Conductor de Vehiculo Liviano", "4": 1.0, "5": 12.0, "6": 1272.0, "7": 15264.0, "8": 1228.9, "9": "SI", "10": 1800.0, "11": 800.0, "12": 19092.9}, {"0": "R", "1": "Regular", "2": "Asuntos del Ciudadano", "3": "Trabajador", "4": 1.0, "5": 12.0, "6": 1394.0, "7": 16728.0, "8": 1340.89, "9": "SI", "10": 1800.0, "11": 800.0, "12": 20668.89}, {"0": "R", "1": "Regular", "2": "Asuntos del Ciudadano", "3": "Secretaria II", "4": 1.0, "5": 12.0, "6": 1388.0, "7": 16656.0, "8": 1335.38, "9": "SI", "10": 1800.0, "11": 800.0, "12": 20591.38}, {"0": "R", "1": "Regular", "2": "Asuntos del Ciudadano", "3": "Auxiliar Administrativo II", "4": 1.0, "5": 12.0, "6": 1520.0, "7": 18240.0, "8": 1456.56, "9": "SI", "10": 1800.0, "11": 800.0, "12": 22296.56}, {"0": "R", "1": "Regular", "2": "Asuntos del Ciudadano", "3": "Conductor de Guagua", "4": 1.0, "5": 12.0, "6": 1371.0, "7": 16452.0, "8": 1319.78, "9": "SI", "10": 1800.0, "11": 800.0, "12": 20371.78}, {"0": "C", "1": "Confianza", "2": "Asuntos del Ciudadano", "3": "Director Asuntos del Ciudadano", "4": 1.0, "5": 12.0, "6": 1055.0, "7": 12660.0, "8": 1029.69, "9": "SI", "10": 1800.0, "11": 800.0, "12": 16289.69}, {"0": "R", "1": "Regular", "2": "Asuntos del Ciudadano", "3": "Conductor de Vehiculo Livianos", "4": 1.0, "5": 12.0, "6": 1203.0, "7": 14436.0, "8": 1165.55, "9": "SI", "10": 1800.0, "11": 800.0, "12": 18201.55}, {"0": "R", "1": "Regular", "2": "Asuntos del Ciudadano", "3": "Conductor de Vehiculo Liviano", "4": 1.0, "5": 12.0, "6": 1422.0, "7": 17064.0, "8": 1366.6, "9": "SI", "10": 1800.0, "11": 800.0, "12": 21030.6}, {"0": "R", "1": "Regular", "2": "Secretar\u00eda Municipal", "3": "Auxiliar Administrativo I", "4": 1.0, "5": 12.0, "6": 1409.0, "7": 16908.0, "8": 1354.66, "9": "SI", "10": 1800.0, "11": 800.0, "12": 20862.66}, {"0": "R", "1": "Regular", "2": "Secretar\u00eda Municipal", "3": "Auxiliar Administativo II", "4": 1.0, "5": 12.0, "6": 1563.0, "7": 18756.0, "8": 1496.03, "9": "SI", "10": 1800.0, "11": 800.0, "12": 22852.03}, {"0": "C", "1": "Confianza", "2": "Secretar\u00eda Municipal", "3": "Secretario Municipal", "4": 1.0, "5": 12.0, "6": 3778.0, "7": 45336.0, "8": 3529.4, "9": "SI", "10": 1800.0, "11": 800.0, "12": 51465.4}, {"0": "R", "1": "Regular", "2": "Secretar\u00eda Municipal", "3": "Auxiliar  Administrativo I", "4": 1.0, "5": 12.0, "6": 1449.0, "7": 17388.0, "8": 1391.38, "9": "SI", "10": 1800.0, "11": 800.0, "12": 21379.38}, {"0": "R", "1": "Regular", "2": "Secretar\u00eda Municipal", "3": "Trabajador", "4": 1.0, "5": 12.0, "6": 1179.0, "7": 14148.0, "8": 1143.52, "9": "SI", "10": 1800.0, "11": 800.0, "12": 17891.52}, {"0": "R", "1": "Regular", "2": "Secretar\u00eda Municipal", "3": "Secretaria II", "4": 1.0, "5": 12.0, "6": 1312.0, "7": 15744.0, "8": 1265.62, "9": "SI", "10": 1800.0, "11": 800.0, "12": 19609.62}, {"0": "R", "1": "Regular", "2": "Secretar\u00eda Municipal", "3": "AUXILIAR DE COMPRAS", "4": 1.0, "5": 12.0, "6": 1626.0, "7": 19512.0, "8": 1553.87, "9": "SI", "10": 1800.0, "11": 800.0, "12": 23665.87}, {"0": "R", "1": "Regular", "2": "Secretar\u00eda Municipal", "3": "Auxiliar Administrativo I", "4": 1.0, "5": 12.0, "6": 1409.0, "7": 16908.0, "8": 1354.66, "9": "SI", "10": 1800.0, "11": 800.0, "12": 20862.66}, {"0": "R", "1": "Regular", "2": "Secretar\u00eda Municipal", "3": "Comprador Oficial", "4": 1.0, "5": 12.0, "6": 1449.0, "7": 17388.0, "8": 1391.38, "9": "SI", "10": 1800.0, "11": 800.0, "12": 21379.38}, {"0": "C", "1": "Confianza", "2": "Auditor\u00eda Interna", "3": "Auditora Interna", "4": 1.0, "5": 12.0, "6": 2858.0, "7": 34296.0, "8": 2684.84, "9": "SI", "10": 1800.0, "11": 800.0, "12": 39580.84}, {"0": "R", "1": "Regular", "2": "Auditor\u00eda Interna", "3": "Secretaria II", "4": 1.0, "5": 12.0, "6": 1660.0, "7": 19920.0, "8": 1585.08, "9": "SI", "10": 1800.0, "11": 800.0, "12": 24105.08}, {"0": "R", "1": "Regular", "2": "Auditor\u00eda Interna", "3": "Contador", "4": 1.0, "5": 12.0, "6": 1466.0, "7": 17592.0, "8": 1406.99, "9": "SI", "10": 1800.0, "11": 800.0, "12": 21598.99}, {"0": "R", "1": "Regular", "2": "Educaci\u00f3n", "3": "Oficinista de Contabilidad", "4": 1.0, "5": 12.0, "6": 1864.0, "7": 22368.0, "8": 1772.35, "9": "SI", "10": 1800.0, "11": 800.0, "12": 26740.35}, {"0": "R", "1": "Regular", "2": "Educaci\u00f3n", "3": "Auxiliar Administrativo III", "4": 1.0, "5": 12.0, "6": 1935.0, "7": 23220.0, "8": 1837.53, "9": "SI", "10": 1800.0, "11": 800.0, "12": 27657.53}, {"0": "R", "1": "Regular", "2": "Educaci\u00f3n", "3": "Oficinista", "4": 1.0, "5": 12.0, "6": 1422.0, "7": 17064.0, "8": 1366.6, "9": "SI", "10": 1800.0, "11": 800.0, "12": 21030.6}, {"0": "R", "1": "Regular", "2": "Educaci\u00f3n", "3": "Oficinista", "4": 1.0, "5": 12.0, "6": 1345.0, "7": 16140.0, "8": 1295.91, "9": "SI", "10": 1800.0, "11": 800.0, "12": 20035.91}, {"0": "R", "1": "Regular", "2": "Educaci\u00f3n", "3": "Trabajador", "4": 1.0, "5": 12.0, "6": 1179.0, "7": 14148.0, "8": 1143.52, "9": "SI", "10": 1800.0, "11": 800.0, "12": 17891.52}, {"0": "R", "1": "Regular", "2": "Planificaci\u00f3n y Desarrollo", "3": "Secretaria I", "4": 1.0, "5": 12.0, "6": 1251.0, "7": 15012.0, "8": 1209.62, "9": "SI", "10": 1800.0, "11": 800.0, "12": 18821.62}, {"0": "R", "1": "Regular", "2": "Planificaci\u00f3n y Desarrollo", "3": "Conductor Veh\u00edculos Livianos", "4": 1.0, "5": 12.0, "6": 1203.0, "7": 14436.0, "8": 1165.55, "9": "SI", "10": 1800.0, "11": 800.0, "12": 18201.55}, {"0": "R", "1": "Regular", "2": "Planificaci\u00f3n y Desarrollo", "3": "Trabajador", "4": 1.0, "5": 12.0, "6": 1179.0, "7": 14148.0, "8": 1143.52, "9": "SI", "10": 1800.0, "11": 800.0, "12": 17891.52}, {"0": "C", "1": "Confianza", "2": "Planificaci\u00f3n y Desarrollo", "3": "Directora Ordenaci\u00f3n Territorial", "4": 1.0, "5": 12.0, "6": 3450.0, "7": 41400.0, "8": 3228.3, "9": "SI", "10": 1800.0, "11": 800.0, "12": 47228.3}, {"0": "R", "1": "Regular", "2": "Planificaci\u00f3n y Desarrollo", "3": "Conductor Veh\u00edculos Livianos", "4": 1.0, "5": 12.0, "6": 1345.0, "7": 16140.0, "8": 1295.91, "9": "SI", "10": 1800.0, "11": 800.0, "12": 20035.91}, {"0": "R", "1": "Regular", "2": "Planificaci\u00f3n y Desarrollo", "3": "Conductor de Vehiculo Pesado", "4": 1.0, "5": 12.0, "6": 1227.0, "7": 14724.0, "8": 1187.59, "9": "SI", "10": 1800.0, "11": 800.0, "12": 18511.59}, {"0": "R", "1": "Regular", "2": "Reciclaje", "3": "Conductor de Veh\u00edculo Pesado", "4": 1.0, "5": 12.0, "6": 1227.0, "7": 14724.0, "8": 1187.59, "9": "SI", "10": 1800.0, "11": 800.0, "12": 18511.59}, {"0": "R", "1": "Regular", "2": "Reciclaje", "3": "Conductor de Veh\u00edculo Pesado", "4": 1.0, "5": 12.0, "6": 1297.0, "7": 15564.0, "8": 1251.85, "9": "SI", "10": 1800.0, "11": 800.0, "12": 19415.85}, {"0": "R", "1": "Regular", "2": "Reciclaje", "3": "Supervisora de Programa de", "4": 1.0, "5": 12.0, "6": 1563.0, "7": 18756.0, "8": 1496.03, "9": "SI", "10": 1800.0, "11": 800.0, "12": 22852.03}, {"0": "R", "1": "Regular", "2": "Reciclaje", "3": "Encargado de Brigada", "4": 1.0, "5": 12.0, "6": 1371.0, "7": 16452.0, "8": 1319.78, "9": "SI", "10": 1800.0, "11": 800.0, "12": 20371.78}, {"0": "R", "1": "Regular", "2": "Reciclaje", "3": "Trabajador", "4": 1.0, "5": 12.0, "6": 1179.0, "7": 14148.0, "8": 1143.52, "9": "SI", "10": 1800.0, "11": 800.0, "12": 17891.52}, {"0": "R", "1": "Regular", "2": "Reciclaje", "3": "Trabajador", "4": 1.0, "5": 12.0, "6": 1179.0, "7": 14148.0, "8": 1143.52, "9": "SI", "10": 1800.0, "11": 800.0, "12": 17891.52}, {"0": "R", "1": "Regular", "2": "Reciclaje", "3": "Trabajador", "4": 1.0, "5": 12.0, "6": 1179.0, "7": 14148.0, "8": 1143.52, "9": "SI", "10": 1800.0, "11": 800.0, "12": 17891.52}]}, "gastos": [{"departamento": "Legislatura Municipal", "gasto": "Empleados Regulares", "monto": 34272.0}, {"departamento": "Legislatura Municipal", "gasto": "Empleados Transitorios", "monto": 14148.0}, {"departamento": "Legislatura Municipal", "gasto": "Seguro Choferil", "monto": 32.0}, {"departamento": "Legislatura Municipal", "gasto": "Seguro Social Federal", "monto": 3826.53}, {"departamento": "Legislatura Municipal", "gasto": "Plan Medico", "monto": 2400.0}, {"departamento": "Legislatura Municipal", "gasto": "Seguro por Desempleo", "monto": 792.0}, {"departamento": "Legislatura Municipal", "gasto": "Bono Navideno", "monto": 1600.0}, {"departamento": "Legislatura Municipal", "gasto": "Materiales de Oficina", "monto": 800.0}, {"departamento": "Legislatura Municipal", "gasto": "Dietas", "monto": 35000.0}, {"departamento": "Legislatura Municipal", "gasto": "Gastos de Viaje", "monto": 2400.0}, {"departamento": "Legislatura Municipal", "gasto": "Cuotas y Suscripciones", "monto": 3900.0}, {"departamento": "Legislatura Municipal", "gasto": "Publicaciones y Anuncios", "monto": 1000.0}, {"departamento": "Oficina del Alcalde(sa)", "gasto": "Empleados Regulares", "monto": 362160.0}, {"departamento": "Oficina del Alcalde(sa)", "gasto": "Empleados Transitorios", "monto": 62400.0}, {"departamento": "Oficina del Alcalde(sa)", "gasto": "Seguro Choferil", "monto": 128.0}, {"departamento": "Oficina del Alcalde(sa)", "gasto": "Seguro Social Federal", "monto": 33396.84}, {"departamento": "Oficina del Alcalde(sa)", "gasto": "Plan Medico", "monto": 24000.0}, {"departamento": "Oficina del Alcalde(sa)", "gasto": "Seguro por Desempleo", "monto": 6336.0}, {"departamento": "Oficina del Alcalde(sa)", "gasto": "Bono Navideno", "monto": 12000.0}, {"departamento": "Oficina del Alcalde(sa)", "gasto": "Materiales de Oficina", "monto": 800.0}, {"departamento": "Oficina del Alcalde(sa)", "gasto": "Materiales de Mantenimiento", "monto": 5500.0}, {"departamento": "Oficina del Alcalde(sa)", "gasto": "Materiales y Suministros de Operacion", "monto": 9000.0}, {"departamento": "Oficina del Alcalde(sa)", "gasto": "Gastos de Auditoria Sencilla (Single Audit)", "monto": 22000.0}, {"departamento": "Oficina del Alcalde(sa)", "gasto": "Servicios Profesionales - No Clasificados", "monto": 131000.0}, {"departamento": "Oficina del Alcalde(sa)", "gasto": "Relaciones Publicas", "monto": 5000.0}, {"departamento": "Oficina del Alcalde(sa)", "gasto": "Gastos de Viaje", "monto": 10000.0}, {"departamento": "Oficina del Alcalde(sa)", "gasto": "Servicios Legales", "monto": 126000.0}, {"departamento": "Oficina del Alcalde(sa)", "gasto": "Cuotas y Suscripciones", "monto": 7500.0}, {"departamento": "Oficina del Alcalde(sa)", "gasto": "Publicaciones y Anuncios", "monto": 17000.0}, {"departamento": "Finanzas", "gasto": "Empleados Regulares", "monto": 226656.0}, {"departamento": "Finanzas", "gasto": "Empleados Transitorios", "monto": 63084.0}, {"departamento": "Finanzas", "gasto": "Vacaciones Acumuladas, Licencia Regular", "monto": 25000.0}, {"departamento": "Finanzas", "gasto": "Vacaciones Acumuladas, Licencia Enfermedad", "monto": 106600.0}, {"departamento": "Finanzas", "gasto": "Seguro Choferil", "monto": 48.0}, {"departamento": "Finanzas", "gasto": "Seguro Social Federal", "monto": 30080.95}, {"departamento": "Finanzas", "gasto": "Plan Medico", "monto": 24000.0}, {"departamento": "Finanzas", "gasto": "Seguro por Desempleo", "monto": 6336.0}, {"departamento": "Finanzas", "gasto": "SINOT", "monto": 8300.0}, {"departamento": "Finanzas", "gasto": "Bono Navideno", "monto": 90675.0}, {"departamento": "Finanzas", "gasto": "Bono Navideno", "monto": 12800.0}, {"departamento": "Finanzas", "gasto": "Beneficios Marginales", "monto": 53143.44}, {"departamento": "Finanzas", "gasto": "Materiales de Oficina", "monto": 7200.0}, {"departamento": "Finanzas", "gasto": "Materiales y Suministros de Operacion", "monto": 200.0}, {"departamento": "Finanzas", "gasto": "Servicios Profesionales - No Clasificados", "monto": 78870.0}, {"departamento": "Finanzas", "gasto": "Servicios No Profesionales", "monto": 400000.0}, {"departamento": "Finanzas", "gasto": "Renta de Edificios, Locales y Terrenos", "monto": 10752.0}, {"departamento": "Finanzas", "gasto": "Mantenimiento de Vehiculos", "monto": 3200.0}, {"departamento": "Finanzas", "gasto": "Beneficio por Fondo del Seguro del Estado", "monto": 365421.98}, {"departamento": "Finanzas", "gasto": "Energia Electrica", "monto": 461391.0}, {"departamento": "Finanzas", "gasto": "Acueducto y Alcantarillados", "monto": 220000.0}, {"departamento": "Finanzas", "gasto": "Telefono y Comunicaciones", "monto": 56000.0}, {"departamento": "Finanzas", "gasto": "Pruebas de Dopaje", "monto": 1500.0}, {"departamento": "Finanzas", "gasto": "Gastos de Viaje", "monto": 8000.0}, {"departamento": "Finanzas", "gasto": "Seguros", "monto": 477000.0}, {"departamento": "Finanzas", "gasto": "Renta de Equipos y Vehiculos", "monto": 182256.0}, {"departamento": "Finanzas", "gasto": "Intereses Cuentas Vendidas", "monto": 32959.72}, {"departamento": "Finanzas", "gasto": "Miscelaneos", "monto": 75725.44}, {"departamento": "Finanzas", "gasto": "Reclamaciones Anos Anteriores", "monto": 124981.0}, {"departamento": "Finanzas", "gasto": "Aportacion al Fondo de Equiparacion", "monto": 1205918.0}, {"departamento": "Finanzas", "gasto": "Aportacion al CRIM", "monto": 141566.0}, {"departamento": "Finanzas", "gasto": "Liquidacion Deuda del CRIM", "monto": 91158.0}, {"departamento": "Finanzas", "gasto": "Transferencias que Salen", "monto": 456743.87}, {"departamento": "Obras Publicas", "gasto": "Empleados Regulares", "monto": 641280.0}, {"departamento": "Obras Publicas", "gasto": "Empleados Transitorios", "monto": 1224714.24}, {"departamento": "Obras Publicas", "gasto": "Seguro Choferil", "monto": 448.0}, {"departamento": "Obras Publicas", "gasto": "Seguro Social Federal", "monto": 150337.36}, {"departamento": "Obras Publicas", "gasto": "Plan Medico", "monto": 120000.0}, {"departamento": "Obras Publicas", "gasto": "Seguro por Desempleo", "monto": 49104.0}, {"departamento": "Obras Publicas", "gasto": "Bono Navideno", "monto": 99200.0}, {"departamento": "Obras Publicas", "gasto": "Materiales de Oficina", "monto": 1100.0}, {"departamento": "Obras Publicas", "gasto": "Materiales de Mantenimiento", "monto": 2700.0}, {"departamento": "Obras Publicas", "gasto": "Combustible y Lubricantes", "monto": 235000.0}, {"departamento": "Obras Publicas", "gasto": "Materiales de Construccion", "monto": 150000.0}, {"departamento": "Obras Publicas", "gasto": "Servicios de Ingenieria y Arquitectura", "monto": 24000.0}, {"departamento": "Obras Publicas", "gasto": "Costos de Construccion", "monto": 350000.0}, {"departamento": "Obras Publicas", "gasto": "Reparacion y Mantenimiento de Estructuras", "monto": 5000.0}, {"departamento": "Obras Publicas", "gasto": "Mantenimiento de Vehiculos", "monto": 300000.0}, {"departamento": "Obras Publicas", "gasto": "Materiales y Suministros de Operacion", "monto": 58000.0}, {"departamento": "Obras Publicas", "gasto": "Compra de Equipos", "monto": 50000.0}, {"departamento": "Obras Publicas", "gasto": "Canon Excavaciones y Demoliciones", "monto": 8000.0}, {"departamento": "Obras Publicas", "gasto": "Renta de Equipos y Vehiculos", "monto": 17900.0}, {"departamento": "Obras Publicas", "gasto": "Disposicion de Desperdicios", "monto": 750000.0}, {"departamento": "Oficina Municipal Manejo de Emergencias", "gasto": "Empleados Regulares", "monto": 243346.68}, {"departamento": "Oficina Municipal Manejo de Emergencias", "gasto": "Empleados Transitorios", "monto": 130020.0}, {"departamento": "Oficina Municipal Manejo de Emergencias", "gasto": "Seguro Choferil", "monto": 160.0}, {"departamento": "Oficina Municipal Manejo de Emergencias", "gasto": "Seguro Social Federal", "monto": 30092.55}, {"departamento": "Oficina Municipal Manejo de Emergencias", "gasto": "Plan Medico", "monto": 34200.0}, {"departamento": "Oficina Municipal Manejo de Emergencias", "gasto": "Seguro por Desempleo", "monto": 9900.0}, {"departamento": "Oficina Municipal Manejo de Emergencias", "gasto": "Bono Navideno", "monto": 20000.0}, {"departamento": "Oficina Municipal Manejo de Emergencias", "gasto": "Materiales de Oficina", "monto": 1700.0}, {"departamento": "Oficina Municipal Manejo de Emergencias", "gasto": "Alimentos", "monto": 10000.0}, {"departamento": "Oficina Municipal Manejo de Emergencias", "gasto": "Gastos de Viaje", "monto": 200.0}, {"departamento": "Oficina Municipal Manejo de Emergencias", "gasto": "Mantenimiento de Vehiculos", "monto": 3100.0}, {"departamento": "Oficina Municipal Manejo de Emergencias", "gasto": "Materiales y Suministros de Operacion", "monto": 7000.0}, {"departamento": "Oficina Municipal Manejo de Emergencias", "gasto": "Renta de Equipos y Vehiculos", "monto": 10000.0}, {"departamento": "Guardia Municipal", "gasto": "Empleados Regulares", "monto": 219701.04}, {"departamento": "Guardia Municipal", "gasto": "Seguro Choferil", "monto": 144.0}, {"departamento": "Guardia Municipal", "gasto": "Seguro Social Federal", "monto": 17480.33}, {"departamento": "Guardia Municipal", "gasto": "Plan Medico", "monto": 19800.0}, {"departamento": "Guardia Municipal", "gasto": "Seguro por Desempleo", "monto": 4356.0}, {"departamento": "Guardia Municipal", "gasto": "Bono Navideno", "monto": 8800.0}, {"departamento": "Guardia Municipal", "gasto": "Materiales de Oficina", "monto": 200.0}, {"departamento": "Guardia Municipal", "gasto": "Materiales de Mantenimiento", "monto": 2000.0}, {"departamento": "Guardia Municipal", "gasto": "Gastos de Viaje", "monto": 200.0}, {"departamento": "Guardia Municipal", "gasto": "Mantenimiento de Vehiculos", "monto": 1100.0}, {"departamento": "Recursos Humanos", "gasto": "Empleados Regulares", "monto": 191880.0}, {"departamento": "Recursos Humanos", "gasto": "Empleados Transitorios", "monto": 64872.0}, {"departamento": "Recursos Humanos", "gasto": "Seguro Choferil", "monto": 16.0}, {"departamento": "Recursos Humanos", "gasto": "Seguro Social Federal", "monto": 20559.53}, {"departamento": "Recursos Humanos", "gasto": "Plan Medico", "monto": 22200.0}, {"departamento": "Recursos Humanos", "gasto": "Seguro por Desempleo", "monto": 5940.0}, {"departamento": "Recursos Humanos", "gasto": "Bono Navideno", "monto": 12000.0}, {"departamento": "Recursos Humanos", "gasto": "Materiales de Oficina", "monto": 400.0}, {"departamento": "Recursos Humanos", "gasto": "Adiestramientos", "monto": 2000.0}, {"departamento": "Recursos Humanos", "gasto": "Reserva", "monto": 83650.0}, {"departamento": "Recreacion y Deportes", "gasto": "Empleados Regulares", "monto": 262404.0}, {"departamento": "Recreacion y Deportes", "gasto": "Empleados Transitorios", "monto": 561384.0}, {"departamento": "Recreacion y Deportes", "gasto": "Seguro Choferil", "monto": 32.0}, {"departamento": "Recreacion y Deportes", "gasto": "Seguro Social Federal", "monto": 66324.58}, {"departamento": "Recreacion y Deportes", "gasto": "Plan Medico", "monto": 51600.0}, {"departamento": "Recreacion y Deportes", "gasto": "Seguro por Desempleo", "monto": 21384.0}, {"departamento": "Recreacion y Deportes", "gasto": "Bono Navideno", "monto": 43200.0}, {"departamento": "Recreacion y Deportes", "gasto": "Materiales de Oficina", "monto": 800.0}, {"departamento": "Recreacion y Deportes", "gasto": "Materiales de Mantenimiento", "monto": 4700.0}, {"departamento": "Recreacion y Deportes", "gasto": "Materiales y Suministros de Operacion", "monto": 36000.0}, {"departamento": "Recreacion y Deportes", "gasto": "Servicios No Profesionales", "monto": 30000.0}, {"departamento": "Recreacion y Deportes", "gasto": "Donaciones", "monto": 30000.0}, {"departamento": "Recreacion y Deportes", "gasto": "Mantenimiento de Vehiculos", "monto": 4400.0}, {"departamento": "Centro de Envejecientes", "gasto": "Empleados Regulares", "monto": 138348.0}, {"departamento": "Centro de Envejecientes", "gasto": "Empleados Transitorios", "monto": 51508.8}, {"departamento": "Centro de Envejecientes", "gasto": "Seguro Choferil", "monto": 48.0}, {"departamento": "Centro de Envejecientes", "gasto": "Seguro Social Federal", "monto": 15258.45}, {"departamento": "Centro de Envejecientes", "gasto": "Plan Medico", "monto": 16800.0}, {"departamento": "Centro de Envejecientes", "gasto": "Seguro por Desempleo", "monto": 4752.0}, {"departamento": "Centro de Envejecientes", "gasto": "Bono Navideno", "monto": 9600.0}, {"departamento": "Centro de Envejecientes", "gasto": "Materiales de Oficina", "monto": 300.0}, {"departamento": "Centro de Envejecientes", "gasto": "Alimentos", "monto": 35000.0}, {"departamento": "Centro de Envejecientes", "gasto": "Materiales y Suministros de Operacion", "monto": 1900.0}, {"departamento": "Centro de Envejecientes", "gasto": "Materiales de Mantenimiento", "monto": 1400.0}, {"departamento": "Aportaciones Federales", "gasto": "Empleados Regulares", "monto": 225144.0}, {"departamento": "Aportaciones Federales", "gasto": "Empleados Transitorios", "monto": 117684.0}, {"departamento": "Aportaciones Federales", "gasto": "Seguro Choferil", "monto": 64.0}, {"departamento": "Aportaciones Federales", "gasto": "Seguro Social Federal", "monto": 27450.34}, {"departamento": "Aportaciones Federales", "gasto": "Plan Medico", "monto": 26400.0}, {"departamento": "Aportaciones Federales", "gasto": "Seguro por Desempleo", "monto": 7920.0}, {"departamento": "Aportaciones Federales", "gasto": "Bono Navideno", "monto": 16000.0}, {"departamento": "Cultura y Turismo", "gasto": "Empleados Regulares", "monto": 75168.0}, {"departamento": "Cultura y Turismo", "gasto": "Empleados Transitorios", "monto": 278040.0}, {"departamento": "Cultura y Turismo", "gasto": "Seguro Choferil", "monto": 32.0}, {"departamento": "Cultura y Turismo", "gasto": "Seguro Social Federal", "monto": 28428.01}, {"departamento": "Cultura y Turismo", "gasto": "Plan Medico", "monto": 18600.0}, {"departamento": "Cultura y Turismo", "gasto": "Seguro por Desempleo", "monto": 9108.0}, {"departamento": "Cultura y Turismo", "gasto": "Bono Navideno", "monto": 18400.0}, {"departamento": "Cultura y Turismo", "gasto": "Materiales de Oficina", "monto": 300.0}, {"departamento": "Cultura y Turismo", "gasto": "Materiales de Mantenimiento", "monto": 100.0}, {"departamento": "Cultura y Turismo", "gasto": "Otros Festivales o Actividades", "monto": 250000.0}, {"departamento": "Asuntos del Ciudadano", "gasto": "Empleados Regulares", "monto": 78852.0}, {"departamento": "Asuntos del Ciudadano", "gasto": "Empleados Transitorios", "monto": 89088.0}, {"departamento": "Asuntos del Ciudadano", "gasto": "Seguro Choferil", "monto": 96.0}, {"departamento": "Asuntos del Ciudadano", "gasto": "Seguro Social Federal", "monto": 13520.61}, {"departamento": "Asuntos del Ciudadano", "gasto": "Plan Medico", "monto": 12600.0}, {"departamento": "Asuntos del Ciudadano", "gasto": "Seguro por Desempleo", "monto": 4356.0}, {"departamento": "Asuntos del Ciudadano", "gasto": "Bono Navideno", "monto": 8800.0}, {"departamento": "Asuntos del Ciudadano", "gasto": "Donaciones", "monto": 40000.0}, {"departamento": "Asuntos del Ciudadano", "gasto": "Donaciones", "monto": 10000.0}, {"departamento": "Asuntos del Ciudadano", "gasto": "Empleados Regulares", "monto": 48648.0}, {"departamento": "Asuntos del Ciudadano", "gasto": "Seguro Choferil", "monto": 16.0}, {"departamento": "Asuntos del Ciudadano", "gasto": "Seguro Social Federal", "monto": 3905.17}, {"departamento": "Asuntos del Ciudadano", "gasto": "Plan Medico", "monto": 5400.0}, {"departamento": "Asuntos del Ciudadano", "gasto": "Seguro por Desempleo", "monto": 1188.0}, {"departamento": "Asuntos del Ciudadano", "gasto": "Bono Navideno", "monto": 2400.0}, {"departamento": "Secretaria Municipal", "gasto": "Empleados Regulares", "monto": 182088.0}, {"departamento": "Secretaria Municipal", "gasto": "Empleados Transitorios", "monto": 235141.92}, {"departamento": "Secretaria Municipal", "gasto": "Seguro Choferil", "monto": 96.0}, {"departamento": "Secretaria Municipal", "gasto": "Seguro Social Federal", "monto": 33509.29}, {"departamento": "Secretaria Municipal", "gasto": "Plan Medico", "monto": 26400.0}, {"departamento": "Secretaria Municipal", "gasto": "Seguro por Desempleo", "monto": 10296.0}, {"departamento": "Secretaria Municipal", "gasto": "Bono Navideno", "monto": 20800.0}, {"departamento": "Secretaria Municipal", "gasto": "Materiales de Oficina", "monto": 6000.0}, {"departamento": "Secretaria Municipal", "gasto": "Mantenimiento de Vehiculos", "monto": 200.0}, {"departamento": "Secretaria Municipal", "gasto": "Publicaciones y Anuncios", "monto": 4800.0}, {"departamento": "Auditoria Interna", "gasto": "Empleados Regulares", "monto": 71808.0}, {"departamento": "Auditoria Interna", "gasto": "Seguro Choferil", "monto": 16.0}, {"departamento": "Auditoria Interna", "gasto": "Seguro Social Federal", "monto": 5676.91}, {"departamento": "Auditoria Interna", "gasto": "Plan Medico", "monto": 5400.0}, {"departamento": "Auditoria Interna", "gasto": "Seguro por Desempleo", "monto": 1188.0}, {"departamento": "Auditoria Interna", "gasto": "Bono Navideno", "monto": 2400.0}, {"departamento": "Auditoria Interna", "gasto": "Materiales de Oficina", "monto": 300.0}, {"departamento": "Educacion", "gasto": "Empleados Regulares", "monto": 92940.0}, {"departamento": "Educacion", "gasto": "Empleados Transitorios", "monto": 72468.0}, {"departamento": "Educacion", "gasto": "Seguro Choferil", "monto": 16.0}, {"departamento": "Educacion", "gasto": "Seguro Social Federal", "monto": 13265.71}, {"departamento": "Educacion", "gasto": "Plan Medico", "monto": 12000.0}, {"departamento": "Educacion", "gasto": "Seguro por Desempleo", "monto": 3960.0}, {"departamento": "Educacion", "gasto": "Bono Navideno", "monto": 8000.0}, {"departamento": "Planificacion y Desarrollo", "gasto": "Empleados Regulares", "monto": 115860.0}, {"departamento": "Planificacion y Desarrollo", "gasto": "Empleados Transitorios", "monto": 185364.0}, {"departamento": "Planificacion y Desarrollo", "gasto": "Seguro Choferil", "monto": 96.0}, {"departamento": "Planificacion y Desarrollo", "gasto": "Seguro Social Federal", "monto": 24206.44}, {"departamento": "Planificacion y Desarrollo", "gasto": "Plan Medico", "monto": 18600.0}, {"departamento": "Planificacion y Desarrollo", "gasto": "Seguro por Desempleo", "monto": 7524.0}, {"departamento": "Planificacion y Desarrollo", "gasto": "Bono Navideno", "monto": 15200.0}, {"departamento": "Planificacion y Desarrollo", "gasto": "Materiales de Oficina", "monto": 100.0}, {"departamento": "Planificacion y Desarrollo", "gasto": "Miscelaneos", "monto": 200.0}, {"departamento": "Reciclaje", "gasto": "Empleados Regulares", "monto": 107940.0}, {"departamento": "Reciclaje", "gasto": "Empleados Transitorios", "monto": 99036.0}, {"departamento": "Reciclaje", "gasto": "Seguro Choferil", "monto": 48.0}, {"departamento": "Reciclaje", "gasto": "Seguro Social Federal", "monto": 16690.46}, {"departamento": "Reciclaje", "gasto": "Plan Medico", "monto": 16800.0}, {"departamento": "Reciclaje", "gasto": "Seguro por Desempleo", "monto": 5544.0}, {"departamento": "Reciclaje", "gasto": "Bono Navideno", "monto": 11200.0}, {"departamento": "Reciclaje", "gasto": "Materiales de Oficina", "monto": 100.0}], "deudas": [{"departamento": "Finanzas", "deuda": "Contribucion sobre Propiedad Exonerada", "monto": 903219.6}, {"departamento": "Finanzas", "deuda": "Contribucion Propiedad No Exonerada (Otras Fuentes Financieras)", "monto": 0.0}, {"departamento": "Finanzas", "deuda": "Amortizacion de Principal de Prestamos", "monto": 530000.0}, {"departamento": "Finanzas", "deuda": "Intereses", "monto": 369170.03}, {"departamento": "Finanzas", "deuda": "Reserva", "monto": 4049.57}], "ingresos": [{"departamento": "Finanzas", "ingreso": "Patentes", "monto": 6733377.16}, {"departamento": "Finanzas", "ingreso": "Impuesto Municipal sobre las Ventas", "monto": 465500.0}, {"departamento": "Finanzas", "ingreso": "Contribucion sobre la Propiedad, Anos Anteriores", "monto": 0.0}, {"departamento": "Finanzas", "ingreso": "Arbitrios de Construccion", "monto": 461240.06}, {"departamento": "Finanzas", "ingreso": "Licencias y Permisos", "monto": 10600.0}, {"departamento": "Finanzas", "ingreso": "Compensacion AEE", "monto": 358130.97}, {"departamento": "Finanzas", "ingreso": "Otros Ingresos Intergubernamentales", "monto": 3074019.0}, {"departamento": "Finanzas", "ingreso": "Disposicion Derperdicios", "monto": 13900.0}, {"departamento": "Finanzas", "ingreso": "Multas", "monto": 3400.0}, {"departamento": "Finanzas", "ingreso": "Intereses en Inversiones", "monto": 60000.0}, {"departamento": "Finanzas", "ingreso": "Ingresos Eventuales", "monto": 36000.0}, {"departamento": "Finanzas", "ingreso": "Renta Locales y Propiedad Municipal", "monto": 145000.0}, {"departamento": "Finanzas", "ingreso": "Otros Ingresos", "monto": 1390000.0}, {"departamento": "Finanzas", "ingreso": "Contribucion Propiedad No Exonerada (Otras Fuentes Financieras)", "monto": 2867723.0}, {"departamento": "Finanzas", "ingreso": "Fiestas Patronales", "monto": 15000.0}], "departamentos": {"legislatura-municipal": {"id": 0, "palabra clave": "legislatura-municipal", "relacionados": []}, "oficina-del-alcalde(sa)": {"id": 1, "palabra clave": "oficina-del-alcalde(sa)", "relacionados": []}, "finanzas": {"id": 2, "palabra clave": "finanzas", "relacionados": []}, "obras-publicas": {"id": 3, "palabra clave": "obras-publicas", "relacionados": []}, "oficina-municipal-manejo-de-emergencias": {"id": 4, "palabra clave": "emergencias", "relacionados": []}, "guardia-municipal": {"id": 5, "palabra clave": "guardia-municipal", "relacionados": []}, "recursos-humanos": {"id": 6, "palabra clave": "recursos-humanos", "relacionados": []}, "recreacion-y-deportes": {"id": 7, "palabra clave": "recreacion-y-deportes", "relacionados": []}, "centro-de-envejecientes": {"id": 8, "palabra clave": "centro-de-envejecientes", "relacionados": []}, "aportaciones-federales": {"id": 28, "palabra clave": "aportaciones-federales", "relacionados": []}, "cultura-y-turismo": {"id": 10, "palabra clave": "cultura-y-turismo", "relacionados": []}, "asuntos-del-ciudadano": {"id": 11, "palabra clave": "asuntos-del-ciudadano", "relacionados": []}, "secretaria-municipal": {"id": 12, "palabra clave": "secretaria-municipal", "relacionados": []}, "auditoria-interna": {"id": 13, "palabra clave": "auditoria-interna", "relacionados": []}, "educacion": {"id": 24, "palabra clave": "educacion", "relacionados": []}, "planificacion-y-desarrollo": {"id": 21, "palabra clave": "planificacion-y-desarrollo", "relacionados": []}, "reciclaje": {"id": 14, "palabra clave": "reciclaje", "relacionados": []}}}